setup.py
brine/__init__.py
brine/barrel.py
brine/cellwork.c
brine/queues.py
brine.egg-info/PKG-INFO
brine.egg-info/SOURCES.txt
brine.egg-info/dependency_links.txt
brine.egg-info/top_level.txt
brine.egg-info/zip-safe