Metadata-Version: 1.1
Name: brine
Version: 1.0.0
Summary: Advanced pickle features, such as anonymous function pickling
Home-page: https://github.com/obriencj/python-brine
Author: Christopher O'Brien
Author-email: obriencj@gmail.com
License: GNU Lesser General Public License
Platform: python2 >= 2.6
Classifier: Intended Audience :: Developers
Classifier: Programming Language :: Python :: 2
Classifier: Topic :: Software Development
Provides: brine
